aconsole/__init__.py
aconsole-0.0.8.dist-info/LICENCE
aconsole-0.0.8.dist-info/METADATA
aconsole-0.0.8.dist-info/WHEEL
aconsole-0.0.8.dist-info/top_level.txt
aconsole-0.0.8.dist-info/RECORD
