Metadata-Version: 2.1
Name: aconsole
Version: 0.0.8
Summary: Async console like GUI built top of tkinter and asyncio.
Home-page: https://github.com/theminad/aconsole
Author: Minad
Author-email: steameetu@gmail.com
License: UNKNOWN
Platform: UNKNOWN
Classifier: Programming Language :: Python :: 3
Classifier: License :: OSI Approved :: MIT License
Classifier: Operating System :: OS Independent
Requires-Python: >=3.6
